dansoto/__init__.py
dansoto/isPrime.py
dansoto-1.dist-info/METADATA
dansoto-1.dist-info/WHEEL
dansoto-1.dist-info/top_level.txt
dansoto-1.dist-info/RECORD
