Metadata-Version: 2.1
Name: dansoto
Version: 1
Summary: Números primos
Home-page: https://github.com/tu_usuario/mi_libreria
Author: Daniel Soto
Author-email: dansoto804@gmail,com
License: MIT
Classifier: Programming Language :: Python :: 3
Classifier: License :: OSI Approved :: MIT License
Classifier: Operating System :: OS Independent
Requires-Python: >=3.6
